PhysicalQuantities/NDict.py
PhysicalQuantities/__init__.py
PhysicalQuantities/binary_units.py
PhysicalQuantities/constants.py
PhysicalQuantities/currency.py
PhysicalQuantities/dBQuantity.py
PhysicalQuantities/decorator.py
PhysicalQuantities/default_units.py
PhysicalQuantities/extend_prefixed.py
PhysicalQuantities/imperial.py
PhysicalQuantities/ipython.py
PhysicalQuantities/more_units.py
PhysicalQuantities/numpywrapper.py
PhysicalQuantities/prefixes.py
PhysicalQuantities/quantity.py
PhysicalQuantities/quantityarray.py
PhysicalQuantities/unit.py
PhysicalQuantities-1.1.1.dist-info/COPYING.rst
PhysicalQuantities-1.1.1.dist-info/METADATA
PhysicalQuantities-1.1.1.dist-info/WHEEL
PhysicalQuantities-1.1.1.dist-info/top_level.txt
PhysicalQuantities-1.1.1.dist-info/RECORD
