Metadata-Version: 2.1
Name: PhysicalQuantities
Version: 1.1.1
Summary: Allow calculations using physical quantities
Home-page: https://github.com/juhasch/PhysicalQuantities
Author: Juergen Hasch
Author-email: juergen.hasch@elbonia.de
License: BSD
Keywords: Physical Quantities IPython
Classifier: Development Status :: 4 - Beta
Classifier: Topic :: Utilities
Classifier: License :: OSI Approved :: BSD License
Requires-Python: >=3.8
License-File: COPYING.rst
Requires-Dist: numpy
Requires-Dist: IPython
Requires-Dist: wrapt
